anemoi/plugins/__init__.py
anemoi/plugins/__main__.py
anemoi/plugins/_version.py
anemoi/plugins/commands/__init__.py
anemoi/plugins/commands/new.py
anemoi/plugins/data/__init__.py
anemoi/plugins/data/common/README.md.mako
anemoi/plugins/data/common/pyproject.toml.mako
anemoi/plugins/data/common/tests/test_plugin.py.mako
anemoi/plugins/data/templates/datasets/create.filter/plugin.py.mako
anemoi/plugins/data/templates/datasets/create.source/plugin.py.mako
anemoi/plugins/data/templates/datasets/create.source/xarray-plugin.py.mako
anemoi/plugins/data/templates/inference/input/plugin.py.mako
anemoi/plugins/data/templates/inference/output/plugin.py.mako
anemoi/plugins/data/templates/inference/post_processing/plugin.py.mako
anemoi/plugins/data/templates/inference/pre_processing/plugin.py.mako
anemoi/plugins/data/templates/inference/runner/plugin.py.mako
anemoi/plugins/data/templates/transform/filter/matching-plugin.py.mako
anemoi/plugins/data/templates/transform/filter/plugin.py.mako
anemoi/plugins/data/templates/transform/source/plugin.py.mako
anemoi_plugins-0.1.0.dist-info/licenses/LICENSE
anemoi_plugins-0.1.0.dist-info/METADATA
anemoi_plugins-0.1.0.dist-info/WHEEL
anemoi_plugins-0.1.0.dist-info/entry_points.txt
anemoi_plugins-0.1.0.dist-info/top_level.txt
anemoi_plugins-0.1.0.dist-info/RECORD
