Metadata-Version: 2.4
Name: anemoi-plugins
Version: 0.1.0
Summary: A package to hold various functions to support training of ML models on ECMWF data.
Author-email: "European Centre for Medium-Range Weather Forecasts (ECMWF)" <software.support@ecmwf.int>
License:                                  Apache License
Project-URL: Documentation, https://anemoi-plugins.readthedocs.io/
Project-URL: Homepage, https://github.com/ecmwf/anemoi-plugins/
Project-URL: Issues, https://github.com/ecmwf/anemoi-plugins/issues
Project-URL: Repository, https://github.com/ecmwf/anemoi-plugins/
Keywords: ai,tools
Classifier: Development Status :: 4 - Beta
Classifier: Intended Audience :: Developers
Classifier: License :: OSI Approved :: Apache Software License
Classifier: Operating System :: OS Independent
Classifier: Programming Language :: Python :: 3 :: Only
Classifier: Programming Language :: Python :: 3.9
Classifier: Programming Language :: Python :: 3.10
Classifier: Programming Language :: Python :: 3.11
Classifier: Programming Language :: Python :: 3.12
Classifier: Programming Language :: Python :: 3.13
Classifier: Programming Language :: Python :: Implementation :: CPython
Classifier: Programming Language :: Python :: Implementation :: PyPy
Requires-Python: >=3.9
License-File: LICENSE
Requires-Dist: anemoi-utils
Requires-Dist: mako
Provides-Extra: all
Provides-Extra: dev
Requires-Dist: anemoi-plugins[all,docs,tests]; extra == "dev"
Provides-Extra: docs
Requires-Dist: nbsphinx; extra == "docs"
Requires-Dist: pandoc; extra == "docs"
Requires-Dist: sphinx; extra == "docs"
Requires-Dist: sphinx-argparse; extra == "docs"
Requires-Dist: sphinx-rtd-theme; extra == "docs"
Provides-Extra: tests
Requires-Dist: pytest; extra == "tests"
Dynamic: license-file
